cpu_code/reorder_buffer.v
module reorder_buffer #(
    parameter SCHEDULER_TAG_BITS = 3,
    parameter REORDER_TAG_BITS = 4
) (
    input wire clk, reset,

    output wire full, empty,

    input wire [1:0] typeIn,
    input wire [4:0] rdIn,
    input wire [31:0] memAddrIn,
    input wire [31:0] dataIn, //from reorder broadcast
    input wire [31:0] pcPlus4In,
    input wire exceptionFlagIn,
    input wire [SCHEDULER_TAG_BITS - 1 : 0] nextSchTag,

    input wire [REORDER_TAG_BITS - 1 : 0] tagA, tagB,
    input wire push_fetch, push_reorder,

    input wire [SCHEDULER_TAG_BITS - 1 : 0] broadcastSchTag,

    output reg [31:0] dataOutReg,
    output reg [4:0] rdOut,
    output reg regWrEn,
    output wire [REORDER_TAG_BITS - 1 : 0] broadcastNextTag,

    output wire [31:0] dataOutA, dataOutB,
    output wire [SCHEDULER_TAG_BITS - 1:0] schTagA, schTagB,
    output wire validA, validB
);
    reg [2**REORDER_TAG_BITS - 1:0] valid = 0;
    reg [2**REORDER_TAG_BITS - 1:0] active = 0;
    reg [1:0] typeOfIns [0: 2**REORDER_TAG_BITS - 1]; //10:Exe, 11:load, 00:store, 01:jump (condition to change)
    reg [4:0] rd [0: 2**REORDER_TAG_BITS - 1];
    reg [31:0] memAddr [0: 2**REORDER_TAG_BITS - 1];
    reg [31:0] data [0: 2**REORDER_TAG_BITS - 1];
    reg [31:0] pcPlus4 [0: 2**REORDER_TAG_BITS - 1];
    reg exceptionFlag [0: 2**REORDER_TAG_BITS - 1];
    reg [SCHEDULER_TAG_BITS - 1:0] schTag [0: 2**REORDER_TAG_BITS - 1];

    reg [SCHEDULER_TAG_BITS - 1:0] old, young;
    reg [REORDER_TAG_BITS - 1:0] searchedTag;
    reg searchedFound;
    //wire [2**REORDER_TAG_BITS-1:0]notEmpty;
    wire notEmpty;
    localparam IDLE = 0;
    localparam PUSH_DATA = 1;
    localparam TAKE_DATA = 1;
    localparam POP_DATA = 1;

    reg stateDecode, stateReorder, stateWB;

    //For debugging only
    wire validDebug = valid[0];
    wire activeDebug = active[0];
    wire [1:0] typeOfInsDebug = typeOfIns[0]; //10:Exe, 11:load, 00:store, 01:jump (condition to change)
    wire [4:0] rdDebug = rd[0];
    wire [31:0] memAddrDebug = memAddr[0];
    wire [31:0] dataDebug = data[0];
    wire [31:0] pcPlus4Debug = pcPlus4[0];
    wire exceptionFlagDebug = exceptionFlag[0];
    wire [SCHEDULER_TAG_BITS - 1:0] schTagDebug = schTag[0];
    //Debugging code ends here

    // assign notEmpty[0] = valid[0];
    // genvar j;
    // generate
    //     for (j = 1; j < 2 ** REORDER_TAG_BITS; j = j+1) begin
    //         assign notEmpty[j] = notEmpty[j-1] | valid[j];
    //     end
    // endgenerate
    assign notEmpty = |valid;
    assign full = (young == old) && notEmpty;
    assign empty = (young == old) && ~notEmpty;

    assign dataOutA = data[tagA];
    assign dataOutB = data[tagB];
    assign schTagA = schTag[tagA];
    assign schTagB = schTag[tagB];
    assign validA = valid[tagA];
    assign vlaidB = valid[tagB];

    assign broadcastNextTag = young + 1;

    always @(posedge clk or posedge reset) begin
        if(reset) begin
            stateDecode <= IDLE;
            stateReorder <= IDLE;
            stateWB <= IDLE;
            old <= 0;
            young <= 0;
        end
    end
    always @(posedge clk ) begin
        case (stateDecode)
            IDLE : begin
                if (push_fetch) begin
                    stateDecode <= PUSH_DATA;
                end
            end
            PUSH_DATA : begin
                young <= young + 1;
                valid[young] <= 0;
                active[young] <= 1;
                typeOfIns[young] <= typeIn;
                rd[young] <= rdIn;
                memAddr[young] <= memAddrIn;
                pcPlus4[young] <= pcPlus4In;
                schTag[young] <= nextSchTag;
                stateDecode <= IDLE;
            end
            default: ;
        endcase
    end

    //content addresable search
    integer i;
    always @(*) begin
        searchedTag = 0;
        searchedFound = 0;
        for (i = 0; i < 2**REORDER_TAG_BITS; i++) begin
            if(active[i] && (schTag[i]==broadcastSchTag)) begin
                searchedTag = i;
                searchedFound = 1;
            end
        end
    end
    always @(posedge clk ) begin
        case (stateReorder)
            IDLE : begin
                if (push_reorder) begin
                    stateReorder <= TAKE_DATA;
                end
            end
            TAKE_DATA : begin
                if(searchedFound) begin
                    data[searchedTag] <= dataIn;
                    exceptionFlag[searchedTag] <= exceptionFlagIn;
                    valid[searchedTag] <= 1;
                end
                stateReorder <= IDLE;
            end
            default: ;
        endcase
    end

    always @(posedge clk ) begin
        case (stateWB)
            IDLE : begin
                regWrEn <= 0;
                if (valid[old] == 1) begin
                    stateWB <= POP_DATA;
                end
            end
            POP_DATA : begin
                dataOutReg <= data[old];
                rdOut <= rd[old];
                regWrEn <= typeOfIns[old][1];
                old <= old + 1;
                valid[old] <= 0;
                active[old] <= 0;
                stateWB <= IDLE;
            end
            default: ;
        endcase
    end
endmodule

cpu_code/tb_rob.v
`timescale 1ns/1ps
module tb_rob (
    
);
    localparam SCHEDULER_TAG_BITS = 3;
    localparam REORDER_TAG_BITS = 4;

    reg clk, reset;
    wire full, empty;
    reg [1:0] typeIn;
    reg [4:0] RdIn;
    reg [31:0] MemAddrIn;
    reg [31:0] DataIn; //from reorder broadcast
    reg [31:0] PcPlus4In;
    reg ExceptionFlagIn;
    reg [SCHEDULER_TAG_BITS - 1 : 0] NextSchTag;

    reg [REORDER_TAG_BITS - 1 : 0] TagA, TagB;
    reg push_fetch=0;
    reg push_reorder=0;

    reg [SCHEDULER_TAG_BITS - 1 : 0] BroadcastSchTag;

    wire [31:0] DataOutReg;
    wire [4:0] RdOut;
    wire RegWrEn;
    wire [REORDER_TAG_BITS - 1 : 0] BroadcastNextTag;

    wire [31:0] dataOutA, dataOutB;
    wire [SCHEDULER_TAG_BITS - 1:0] SchTagA, SchTagB;
    wire validA, validB;

    reorder_buffer dut(
        clk, reset, full, empty, typeIn, RdIn, MemAddrIn, DataIn,
        PcPlus4In, ExceptionFlagIn, NextSchTag, TagA, TagB,
        push_fetch, push_reorder, BroadcastSchTag, DataOutReg, RdOut,
        RegWrEn, BroadcastNextTag, dataOutA, dataOutB, SchTagA, SchTagB, validA, validB
    );

    initial begin
        clk = 0;
        reset = 1;
        # 13
        reset = 0;
    end

    always #5 clk = ~clk;

    task drive_decode;
        input [1:0] typeInp;
        input [4:0] RdInp;
        input [31:0] MemAddrInp;
        input [31:0] PcPlus4Inp;
        input [SCHEDULER_TAG_BITS - 1 : 0] NextSchTagInp;
        input [REORDER_TAG_BITS - 1 : 0] TagAInp, TagBInp;

        begin
            @(negedge clk);
            push_fetch = 1;
            typeIn = typeInp;
            RdIn = RdInp;
            MemAddrIn = MemAddrInp;
            PcPlus4In = PcPlus4Inp;
            NextSchTag = NextSchTagInp;
            TagA = TagAInp;
            TagB = TagBInp;
            @(negedge clk);
            push_fetch = 0;
        end
    endtask

    task drive_reorder;
        input [31:0] DataInp;
        input [SCHEDULER_TAG_BITS - 1 : 0] BroadcastSchTagInp;
        input ExceptionFlagInp;
        begin
            @(negedge clk);
            push_reorder = 1;
            DataIn = DataInp;
            BroadcastSchTag = BroadcastSchTagInp;
            ExceptionFlagIn = ExceptionFlagInp;
            @(negedge clk);
            push_reorder = 0;
        end
    endtask

    initial begin
        # 13
        @(posedge clk);
        drive_decode(2'd0, 5'd1, 32'd13, 32'd14, 3, 2, 1);
        TagA = 0;
        @(posedge clk);
        drive_decode(2'd0, 5'd1, 32'd13, 32'd14, 0, 2, 1);
        TagA = 1;
        @(posedge clk);
        drive_reorder(32'd67, 3, 0);
        @(posedge clk);

        # 30;
        $finish;
    end

    initial begin
        $dumpfile("tb_rob.vcd");
        $dumpvars(0, tb_rob);
    end

endmodule

cpu_code/tb_rob.vcd
$date
	Sun May 31 15:07:06 2026
$end
$version
	Icarus Verilog
$end
$timescale
	1ps
$end
$scope module tb_rob $end
$var wire 1 ! validB $end
$var wire 1 " validA $end
$var wire 1 # full $end
$var wire 1 $ empty $end
$var wire 32 % dataOutB [31:0] $end
$var wire 32 & dataOutA [31:0] $end
$var wire 3 ' SchTagB [2:0] $end
$var wire 3 ( SchTagA [2:0] $end
$var wire 1 ) RegWrEn $end
$var wire 5 * RdOut [4:0] $end
$var wire 32 + DataOutReg [31:0] $end
$var wire 4 , BroadcastNextTag [3:0] $end
$var parameter 32 - REORDER_TAG_BITS $end
$var parameter 32 . SCHEDULER_TAG_BITS $end
$var reg 3 / BroadcastSchTag [2:0] $end
$var reg 32 0 DataIn [31:0] $end
$var reg 1 1 ExceptionFlagIn $end
$var reg 32 2 MemAddrIn [31:0] $end
$var reg 3 3 NextSchTag [2:0] $end
$var reg 32 4 PcPlus4In [31:0] $end
$var reg 5 5 RdIn [4:0] $end
$var reg 4 6 TagA [3:0] $end
$var reg 4 7 TagB [3:0] $end
$var reg 1 8 clk $end
$var reg 1 9 push_fetch $end
$var reg 1 : push_reorder $end
$var reg 1 ; reset $end
$var reg 2 < typeIn [1:0] $end
$scope module dut $end
$var wire 3 = broadcastSchTag [2:0] $end
$var wire 1 8 clk $end
$var wire 32 > dataDebug [31:0] $end
$var wire 32 ? dataIn [31:0] $end
$var wire 32 @ dataOutA [31:0] $end
$var wire 32 A dataOutB [31:0] $end
$var wire 1 $ empty $end
$var wire 1 B exceptionFlagDebug $end
$var wire 1 1 exceptionFlagIn $end
$var wire 1 # full $end
$var wire 32 C memAddrDebug [31:0] $end
$var wire 32 D memAddrIn [31:0] $end
$var wire 3 E nextSchTag [2:0] $end
$var wire 32 F pcPlus4Debug [31:0] $end
$var wire 32 G pcPlus4In [31:0] $end
$var wire 1 9 push_fetch $end
$var wire 1 : push_reorder $end
$var wire 5 H rdDebug [4:0] $end
$var wire 5 I rdIn [4:0] $end
$var wire 1 ; reset $end
$var wire 3 J schTagA [2:0] $end
$var wire 3 K schTagB [2:0] $end
$var wire 3 L schTagDebug [2:0] $end
$var wire 4 M tagA [3:0] $end
$var wire 4 N tagB [3:0] $end
$var wire 2 O typeIn [1:0] $end
$var wire 2 P typeOfInsDebug [1:0] $end
$var wire 1 ! validB $end
$var wire 1 Q vlaidB $end
$var wire 1 R validDebug $end
$var wire 1 " validA $end
$var wire 1 S notEmpty $end
$var wire 4 T broadcastNextTag [3:0] $end
$var wire 1 U activeDebug $end
$var parameter 32 V IDLE $end
$var parameter 32 W POP_DATA $end
$var parameter 32 X PUSH_DATA $end
$var parameter 32 Y REORDER_TAG_BITS $end
$var parameter 32 Z SCHEDULER_TAG_BITS $end
$var parameter 32 [ TAKE_DATA $end
$var reg 16 \ active [15:0] $end
$var reg 32 ] dataOutReg [31:0] $end
$var reg 3 ^ old [2:0] $end
$var reg 5 _ rdOut [4:0] $end
$var reg 1 ) regWrEn $end
$var reg 1 ` searchedFound $end
$var reg 4 a searchedTag [3:0] $end
$var reg 1 b stateDecode $end
$var reg 1 c stateReorder $end
$var reg 1 d stateWB $end
$var reg 16 e valid [15:0] $end
$var reg 3 f young [2:0] $end
$var integer 32 g i [31:0] $end
$upscope $end
$scope task drive_decode $end
$var reg 32 h MemAddrInp [31:0] $end
$var reg 3 i NextSchTagInp [2:0] $end
$var reg 32 j PcPlus4Inp [31:0] $end
$var reg 5 k RdInp [4:0] $end
$var reg 4 l TagAInp [3:0] $end
$var reg 4 m TagBInp [3:0] $end
$var reg 2 n typeInp [1:0] $end
$upscope $end
$scope task drive_reorder $end
$var reg 3 o BroadcastSchTagInp [2:0] $end
$var reg 32 p DataInp [31:0] $end
$var reg 1 q ExceptionFlagInp $end
$upscope $end
$upscope $end
$enddefinitions $end
$comment Show the parameter values. $end
$dumpall
b1 [
b11 Z
b100 Y
b1 X
b1 W
b0 V
b11 .
b100 -
$end
#0
$dumpvars
xq
bx p
bx o
bx n
bx m
bx l
bx k
bx j
bx i
bx h
b10000 g
b0 f
b0 e
0d
0c
0b
b0 a
0`
bx _
b0 ^
bx ]
b0 \
0U
b1 T
0S
0R
xQ
bx P
bx O
bx N
bx M
bx L
bx K
bx J
bx I
bx H
bx G
bx F
bx E
bx D
bx C
xB
bx A
bx @
bx ?
bx >
bx =
bx <
1;
0:
09
08
bx 7
bx 6
bx 5
bx 4
bx 3
bx 2
x1
bx 0
bx /
b1 ,
bx +
bx *
x)
bx (
bx '
bx &
bx %
1$
0#
x"
z!
$end
#5000
0)
18
#10000
08
#13000
0;
#15000
b1 m
b10 l
b11 i
b1110 j
b1101 h
b1 k
b0 n
18
#20000
0Q
b1 7
b1 N
0"
b10 6
b10 M
b11 3
b11 E
b1110 4
b1110 G
b1101 2
b1101 D
b1 5
b1 I
b0 <
b0 O
19
08
#25000
1b
18
#30000
b0 6
b0 M
09
08
#35000
b10000 g
1U
0$
0b
b11 (
b11 J
b11 L
b1110 F
b1101 C
b1 H
b0 P
b1 \
b10 ,
b10 T
b1 f
b0 i
18
#40000
bx (
bx J
b10 6
b10 M
b0 3
b0 E
19
08
#45000
1b
18
#50000
b1 6
b1 M
09
08
#55000
b10000 g
0b
b0 (
b0 J
b0 '
b0 K
b11 \
b11 ,
b11 T
b10 f
0q
b11 o
b1000011 p
18
#60000
1`
b10000 g
01
b11 /
b11 =
b1000011 0
b1000011 ?
1:
08
#65000
1c
18
#70000
0:
08
#75000
1R
0c
1S
b1 e
0B
b1000011 >
18
#80000
08
#85000
1d
18
#90000
08
#95000
b10000 g
0`
0U
0R
0d
b10 \
0S
b0 e
b1 ^
b1 *
b1 _
b1000011 +
b1000011 ]
18
